.flake8
.gitignore
.gitlab-ci.yml
LICENSE
README.md
requirements.txt
setup.py
test.py
html_stripper/__init__.py
html_stripper.egg-info/PKG-INFO
html_stripper.egg-info/SOURCES.txt
html_stripper.egg-info/dependency_links.txt
html_stripper.egg-info/top_level.txt