Metadata-Version: 2.1
Name: html-stripper
Version: 0.3
Summary: A simple package to extract text from (even broken/invalid) HTML
Home-page: https://gitlab.com/helb/html_stripper
Author: Jiri Helebrant
Author-email: helb@helb.cz
License: UNKNOWN
Keywords: html
Platform: UNKNOWN
Classifier: Development Status :: 4 - Beta
Classifier: Programming Language :: Python
Classifier: Programming Language :: Python :: 3
Classifier: License :: OSI Approved :: GNU General Public License v3 (GPLv3)
Classifier: Operating System :: OS Independent
Requires-Python: >=3.6
